sddmp/common.py
sddmp/config.py
sddmp/demo.py
sddmp/filesystem/__init__.py
sddmp/filesystem/directory.py
sddmp/filesystem/file.py
sddmp/filesystem/filesystem.py
sddmp/filesystem/filetree.py
sddmp/generate.py
sddmp/metadata/__init__.py
sddmp/metadata/metadata.py
sddmp/metadata/person.py
sddmp/metadata/schema_org_validator.py
sddmp/metadata/thing.py
sddmp/outputs/__init__.py
sddmp/outputs/directory_page.py
sddmp/outputs/html_page.py
sddmp/outputs/plots/__init__.py
sddmp/outputs/plots/base_plot.py
sddmp/outputs/plots/palette.py
sddmp/outputs/plots/pie_plot.py
sddmp/outputs/plots/plot_generator.py
sddmp/outputs/reference_page.py
sddmp/outputs/static/js/jquery-ui.min.js
sddmp/outputs/static/js/script.js
sddmp/outputs/static/styles/custom.css
sddmp/outputs/static/styles/styles.css
sddmp/outputs/templates/components/body/heading.html.j2
sddmp/outputs/templates/components/body/large_card.html.j2
sddmp/outputs/templates/components/body/person_card.html.j2
sddmp/outputs/templates/components/body/plot_div.html.j2
sddmp/outputs/templates/components/body/small_card.html.j2
sddmp/outputs/templates/components/body/table.html.j2
sddmp/outputs/templates/components/topbar/nav_alert.html.j2
sddmp/outputs/templates/directory.html.j2
sddmp/outputs/templates/partials/footer.html.j2
sddmp/outputs/templates/partials/head.html.j2
sddmp/outputs/templates/partials/layout.html.j2
sddmp/outputs/templates/partials/scripts.html.j2
sddmp/outputs/templates/partials/side_nav.html.j2
sddmp/outputs/templates/partials/top_nav.html.j2
sddmp/outputs/templates/reference.html.j2
sddmp/resources/README_example.yaml
sddmp/resources/demo_structure.txt
sddmp/util/file_operations.py
sddmp-0.1.8.dist-info/METADATA
sddmp-0.1.8.dist-info/WHEEL
sddmp-0.1.8.dist-info/RECORD
