Metadata-Version: 2.1
Name: sddmp
Version: 0.1.8
Summary: A Self Documenting Data Management Plan (SDDMP)
Author: Jonathan Hartman
Author-email: hartman@itc.rwth-aachen.de
Requires-Python: >=3.10,<4.0
Classifier: Programming Language :: Python :: 3
Classifier: Programming Language :: Python :: 3.10
Classifier: Programming Language :: Python :: 3.11
Classifier: Programming Language :: Python :: 3.12
Requires-Dist: jinja2 (>=3.1.3,<4.0.0)
Requires-Dist: pandas (>=2.1.3,<3.0.0)
Requires-Dist: plotly (>=5.18.0,<6.0.0)
Requires-Dist: pyyaml (>=6.0.1,<7.0.0)
Requires-Dist: rdflib (>=7.0.0,<8.0.0)
Requires-Dist: requests (>=2.31.0,<3.0.0)
Requires-Dist: toml (>=0.10.2,<0.11.0)
